<annotation><folder>VOC2014</folder><filename>472.jpg</filename><source><database>MS COCO 2014</database><annotation>MS COCO 2014</annotation><image>Flickr</image></source><size><width>1378</width><height>1160</height><depth>3</depth></size><segmented>0</segmented><object><name>NineDash</name><bndbox><xmin>884</xmin><ymin>528</ymin><xmax>1029</xmax><ymax>707</ymax></bndbox></object><object><name>NineDash</name><bndbox><xmin>654</xmin><ymin>549</ymin><xmax>862</xmax><ymax>707</ymax></bndbox></object></annotation>